ein/__init__.py
ein/_version.py
ein/config.py
ein/eventful.py
ein/flask.py
ein/utils.py
ein/_flask/__init__.py
ein/_flask/config.py
ein12-0.0.2.dist-info/DESCRIPTION.rst
ein12-0.0.2.dist-info/METADATA
ein12-0.0.2.dist-info/RECORD
ein12-0.0.2.dist-info/WHEEL
ein12-0.0.2.dist-info/metadata.json
ein12-0.0.2.dist-info/pbr.json
ein12-0.0.2.dist-info/top_level.txt
