Metadata-Version: 2.0
Name: ein12
Version: 0.0.2
Summary: Configuration for any framework.
Home-page: https://github.com/akatrevorjay/ein
Author: Trevor Joynson
Author-email: github@skywww.net
License: GPL
Keywords: 12factor
Requires-Dist: six
Requires-Dist: attrs
Requires-Dist: uninhibited
